<?xml version="1.0" encoding="UTF-8"?>
<conf_file>
  <info>
    <min_obj_agg />
    <header />
    <addon_sorting />
  </info>
  <temp_table_ref src="rsran/counters/FVCCBU.xml">
    <counters>
      <counter alias="vcBdlOutBwUtiClass1_1">nvl(SUM(vcBdlOutBwUtiClass1),0)</counter>
      <counter alias="vcBdlOutBwUtiClass2_1">nvl(SUM(vcBdlOutBwUtiClass2),0)</counter>
      <counter alias="vcBdlOutBwUtiClass3_1">nvl(SUM(vcBdlOutBwUtiClass3),0)</counter>
      <counter alias="vcBdlOutBwUtiClass4_1">nvl(SUM(vcBdlOutBwUtiClass4),0)</counter>
      <counter alias="vcBdlOutBwUtiClass5_1">nvl(SUM(vcBdlOutBwUtiClass5),0)</counter>
      <counter alias="vcBdlInBwUtiClass1_1">nvl(SUM(vcBdlInBwUtiClass1),0)</counter>
      <counter alias="vcBdlInBwUtiClass2_1">nvl(SUM(vcBdlInBwUtiClass2),0)</counter>
      <counter alias="vcBdlInBwUtiClass3_1">nvl(SUM(vcBdlInBwUtiClass3),0)</counter>
      <counter alias="vcBdlInBwUtiClass4_1">nvl(SUM(vcBdlInBwUtiClass4),0)</counter>
      <counter alias="vcBdlInBwUtiClass5_1">nvl(SUM(vcBdlInBwUtiClass5),0)</counter>
      <counter alias="vcBdlBwConfig_1">nvl(AVG(vcBdlBwConfig),0)</counter>
      <counter alias="vcBdlOutPeakThrput_1">nvl(MAX(vcBdlOutPeakThrput),0)</counter>
      <counter alias="vcBdlInPeakThrput_1">nvl(MAX(vcBdlInPeakThrput),0)</counter>
    </counters>
  </temp_table_ref>
</conf_file>

